locast/__init__.py
locast/candle/__init__.py
locast/candle/candle.py
locast/candle/candle_utility.py
locast/candle/dydx/__init__.py
locast/candle/dydx/dydx_candle_mapping.py
locast/candle/dydx/dydx_resolution.py
locast/candle/exchange.py
locast/candle/exchange_candle_mapper.py
locast/candle/exchange_candle_mapping.py
locast/candle/exchange_resolution.py
locast/candle_fetcher/__init__.py
locast/candle_fetcher/api_fetcher.py
locast/candle_fetcher/candle_fetcher.py
locast/candle_fetcher/dydx/__init__.py
locast/candle_fetcher/dydx/api_fetcher/__init__.py
locast/candle_fetcher/dydx/api_fetcher/datetime_format.py
locast/candle_fetcher/dydx/api_fetcher/dydx_fetcher.py
locast/candle_fetcher/dydx/api_fetcher/dydx_v4_fetcher.py
locast/candle_fetcher/dydx/candle_fetcher/__init__.py
locast/candle_fetcher/dydx/candle_fetcher/dydx_candle_fetcher.py
locast/candle_fetcher/exceptions.py
locast/candle_storage/__init__.py
locast/candle_storage/candle_storage.py
locast/candle_storage/cluster_info.py
locast/candle_storage/database_candle_mapper.py
locast/candle_storage/database_candle_mapping.py
locast/candle_storage/sql/__init__.py
locast/candle_storage/sql/sqlite_candle_mapping.py
locast/candle_storage/sql/sqlite_candle_storage.py
locast/candle_storage/sql/table_utility.py
locast/candle_storage/sql/tables.py
locast/logging_functions.py
locast/main.py
locast/py.typed
locast/store_manager/__init__.py
locast/store_manager/store_manager.py
locast-0.1.9.dist-info/LICENSE
locast-0.1.9.dist-info/METADATA
locast-0.1.9.dist-info/WHEEL
locast-0.1.9.dist-info/RECORD
