Metadata-Version: 2.3
Name: locast
Version: 0.1.9
Summary: 
Author: sirEven
Author-email: sir_even@icloud.com
Requires-Python: >=3.10,<4
Classifier: Programming Language :: Python :: 3
Classifier: Programming Language :: Python :: 3.10
Classifier: Programming Language :: Python :: 3.11
Classifier: Programming Language :: Python :: 3.12
Classifier: Programming Language :: Python :: 3.13
Requires-Dist: dydx-v4-client (>=1.1.3,<2.0.0)
Requires-Dist: python-dateutil (>=2.9.0.post0,<3.0.0)
Requires-Dist: sir-utilities (>=0.1.3,<0.2.0)
Requires-Dist: sqlmodel (>=0.0.21,<0.0.22)
